binteger.py
binteger-0.15.1.dist-info/LICENSE
binteger-0.15.1.dist-info/METADATA
binteger-0.15.1.dist-info/WHEEL
binteger-0.15.1.dist-info/RECORD
